RStoolkit/__init__.py
RStoolkit/common.py
RStoolkit/geometry.py
RStoolkit/image.py
RStoolkit/video.py
RStoolkit-1.0.7.dist-info/DESCRIPTION.rst
RStoolkit-1.0.7.dist-info/METADATA
RStoolkit-1.0.7.dist-info/RECORD
RStoolkit-1.0.7.dist-info/WHEEL
RStoolkit-1.0.7.dist-info/metadata.json
RStoolkit-1.0.7.dist-info/top_level.txt
RStoolkit-1.0.7.dist-info/zip-safe
