Metadata-Version: 2.0
Name: RStoolkit
Version: 1.0.7
Summary: A powerful and useful package for remote sensing image&video preocessing.
Home-page: https://github.com/zhaoxuhui/RStoolkit
Author: zhaoxuhui
Author-email: zhaoxuhui@whu.edu.cn
License: MIT
Keywords: RemoteSensing Image Video
Platform: UNKNOWN
Classifier: License :: OSI Approved :: MIT License
Classifier: Programming Language :: Python
Classifier: Operating System :: OS Independent
Classifier: Topic :: Scientific/Engineering :: Astronomy
Classifier: Topic :: Scientific/Engineering :: GIS
Classifier: Topic :: Scientific/Engineering :: Mathematics
Classifier: Intended Audience :: Science/Research
Classifier: Intended Audience :: Developers
Classifier: Intended Audience :: Information Technology
Requires-Dist: opencv-contrib-python (>=3.1.0)
Requires-Dist: gdal (>=2.1.4)
